hzdplugins/__init__.py
hzdplugins/aiidaplugins/__init__.py
hzdplugins/aiidaplugins/constants.py
hzdplugins/aiidaplugins/deprecated.py
hzdplugins/aiidaplugins/info.py
hzdplugins/aiidaplugins/inputgenerator.py
hzdplugins/aiidaplugins/io.py
hzdplugins/aiidaplugins/serverio.py
hzdplugins/aiidaplugins/submit.py
hzdplugins/aiidaplugins/utilities.py
hzdplugins/aiidaplugins/adsorbates/CH.mol
hzdplugins/aiidaplugins/adsorbates/CH2.mol
hzdplugins/aiidaplugins/adsorbates/CH2OH.mol
hzdplugins/aiidaplugins/adsorbates/CH3.mol
hzdplugins/aiidaplugins/adsorbates/CH3O.mol
hzdplugins/aiidaplugins/adsorbates/CHO.mol
hzdplugins/aiidaplugins/adsorbates/CHOH.mol
hzdplugins/aiidaplugins/adsorbates/CO.mol
hzdplugins/aiidaplugins/adsorbates/COH.mol
hzdplugins/aiidaplugins/adsorbates/COOH.mol
hzdplugins/aiidaplugins/adsorbates/HCOO.mol
hzdplugins/aiidaplugins/adsorbates/NH.mol
hzdplugins/aiidaplugins/adsorbates/NH2.mol
hzdplugins/aiidaplugins/adsorbates/OH.mol
hzdplugins/aiidaplugins/adsorbates/OOH.mol
hzdplugins/aiidaplugins/adsorbates/__init__.py
hzdplugins/deepmdplugins/__init__.py
hzdplugins/deepmdplugins/submit.py
hzdplugins/scripts/__init__.py
hzdplugins/scripts/pdos.py
hzdplugins/scripts/wannier.py
hzdplugins/structure/__init__.py
hzdplugins/structure/build.py
hzdplugins/structure/math.py
hzdplugins/workflows/__init__.py
hzdplugins/workflows/data.py
hzdplugins/workflows/results_pdos.py
hzdplugins/workflows/wannier.py
hzdplugins/workflows/wannier_output.py
hzdplugins-0.0.57.dist-info/METADATA
hzdplugins-0.0.57.dist-info/WHEEL
hzdplugins-0.0.57.dist-info/top_level.txt
hzdplugins-0.0.57.dist-info/RECORD
