Metadata-Version: 2.1
Name: hzdplugins
Version: 0.0.57
Summary: plugins for my own research
Home-page: UNKNOWN
Author: Zheng-Da He
Author-email: z.he@fz-juelich.de, jameshzd@mail.ustc.edu.cn, zhengdahe.electrocatalysis@gmail.com
License: MIT
Platform: UNKNOWN
Requires-Dist: ase
Requires-Dist: pymatgen
Requires-Dist: aiida-core
Requires-Dist: aiida-quantumespresso
Requires-Dist: qeschema
